{
	"name": "bronze_sedem_productos",
	"properties": {
		"linkedServiceName": {
			"referenceName": "db_subsidio",
			"type": "LinkedServiceReference"
		},
		"folder": {
			"name": "bronze/sedem"
		},
		"annotations": [],
		"type": "AzureSqlTable",
		"schema": [
			{
				"name": "producto_id",
				"type": "varchar"
			},
			{
				"name": "empresa_id",
				"type": "varchar"
			},
			{
				"name": "nombre",
				"type": "varchar"
			},
			{
				"name": "categoria",
				"type": "varchar"
			},
			{
				"name": "presentacion",
				"type": "varchar"
			},
			{
				"name": "estado",
				"type": "varchar"
			}
		],
		"typeProperties": {
			"schema": "bronze",
			"table": "sedem_productos"
		}
	}
}